recinam/__init__.py
recinam/recinam.py
recinam-0.0.1.dist-info/DESCRIPTION.rst
recinam-0.0.1.dist-info/METADATA
recinam-0.0.1.dist-info/RECORD
recinam-0.0.1.dist-info/WHEEL
recinam-0.0.1.dist-info/metadata.json
recinam-0.0.1.dist-info/top_level.txt
