Metadata-Version: 2.0
Name: recinam
Version: 0.0.1
Summary: Nucleic Acid Memory Reciprocal Converter
Home-page: https://github.com/mehdiforoozandeh/recinam
Author: Mehdi Foroozandeh, Sasan Ashrafi
Author-email: mehdiforoozandehsh@gmail.com , sasan.ashrafi.m@gmail.com
License: UNKNOWN
Platform: UNKNOWN
Classifier: Programming Language :: Python :: 2.7
Classifier: License :: OSI Approved :: MIT License
Classifier: Operating System :: OS Independent
